Metadata-Version: 2.1
Name: diff-plonk
Version: 0.4
Summary: Diffusion Geolocalization package for PLONK models
Author: Nicolas Dufour
Requires-Python: >=3.10
License-File: LICENSE
Requires-Dist: torch
Requires-Dist: torchvision
Requires-Dist: numpy
Requires-Dist: pandas
Requires-Dist: transformers
Requires-Dist: accelerate
Requires-Dist: geoopt
Requires-Dist: geos
Requires-Dist: scipy ==1.13.1
Requires-Dist: einops
Requires-Dist: torchdiffeq
Provides-Extra: demo
Requires-Dist: streamlit ; extra == 'demo'
Requires-Dist: streamlit-extras ; extra == 'demo'
Requires-Dist: plotly ; extra == 'demo'
Provides-Extra: train
Requires-Dist: wandb ; extra == 'train'
Requires-Dist: hydra-core ; extra == 'train'
Requires-Dist: pytorch-lightning ; extra == 'train'
Requires-Dist: scikit-learn ; extra == 'train'
Requires-Dist: reverse-geocoder ; extra == 'train'
Requires-Dist: matplotlib ; extra == 'train'
Requires-Dist: webdataset ==0.2.57 ; extra == 'train'
